talksheet/__init__.py
talksheet/sample_data/users.csv
talksheet/talksheet.css
talksheet/talksheet.py
talksheet-0.9.0.dist-info/WHEEL
talksheet-0.9.0.dist-info/entry_points.txt
talksheet-0.9.0.dist-info/METADATA
talksheet-0.9.0.dist-info/RECORD
